ftgo/__init__.py
ftgo/historical.py
ftgo/holdings.py
ftgo/infos.py
ftgo/search.py
ftgo-1.0.0.dist-info/licenses/LICENSE
ftgo-1.0.0.dist-info/METADATA
ftgo-1.0.0.dist-info/WHEEL
ftgo-1.0.0.dist-info/entry_points.txt
ftgo-1.0.0.dist-info/top_level.txt
ftgo-1.0.0.dist-info/RECORD
