Metadata-Version: 2.4
Name: ftgo
Version: 1.0.0
Summary: A Python library for fetching financial data from FT Markets
Home-page: https://github.com/gohibiki/ftgo
Author: gohibiki
Author-email: gohibiki <gohibiki@protonmail.com>
Maintainer-email: gohibiki <gohibiki@protonmail.com>
License-Expression: MIT
Project-URL: Homepage, https://github.com/gohibiki/ftgo
Project-URL: Repository, https://github.com/gohibiki/ftgo
Project-URL: Documentation, https://github.com/gohibiki/ftgo#readme
Project-URL: Bug Reports, https://github.com/gohibiki/ftgo/issues
Project-URL: Changelog, https://github.com/gohibiki/ftgo/blob/main/CHANGELOG.md
Keywords: finance,stocks,etf,historical-data,financial-analysis,market-data,ft-markets,financial-times
Classifier: Development Status :: 4 - Beta
Classifier: Intended Audience :: Financial and Insurance Industry
Classifier: Intended Audience :: Developers
Classifier: Operating System :: OS Independent
Classifier: Programming Language :: Python :: 3
Classifier: Programming Language :: Python :: 3.7
Classifier: Programming Language :: Python :: 3.8
Classifier: Programming Language :: Python :: 3.9
Classifier: Programming Language :: Python :: 3.10
Classifier: Programming Language :: Python :: 3.11
Classifier: Programming Language :: Python :: 3.12
Classifier: Topic :: Office/Business :: Financial
Classifier: Topic :: Software Development :: Libraries :: Python Modules
Classifier: Topic :: Internet :: WWW/HTTP :: Dynamic Content
Requires-Python: >=3.7
License-File: LICENSE
Requires-Dist: cloudscraper>=1.2.68
Requires-Dist: pandas>=1.3.0
Requires-Dist: beautifulsoup4>=4.11.0
Provides-Extra: dev
Requires-Dist: pytest>=7.0.0; extra == "dev"
Requires-Dist: pytest-cov>=4.0.0; extra == "dev"
Requires-Dist: black>=23.0.0; extra == "dev"
Requires-Dist: flake8>=6.0.0; extra == "dev"
Requires-Dist: mypy>=1.0.0; extra == "dev"
Requires-Dist: isort>=5.12.0; extra == "dev"
Provides-Extra: examples
Requires-Dist: matplotlib>=3.6.0; extra == "examples"
Requires-Dist: jupyter>=1.0.0; extra == "examples"
Dynamic: author
Dynamic: home-page
Dynamic: license-file
Dynamic: requires-python
